CONTRIBUTING.md
MANIFEST.in
README.rst
setup.py
docs/HISTORY.txt
docs/LICENSE.GPL
docs/LICENSE.txt
eea/__init__.py
eea.volto.policy.egg-info/PKG-INFO
eea.volto.policy.egg-info/SOURCES.txt
eea.volto.policy.egg-info/dependency_links.txt
eea.volto.policy.egg-info/entry_points.txt
eea.volto.policy.egg-info/namespace_packages.txt
eea.volto.policy.egg-info/not-zip-safe
eea.volto.policy.egg-info/requires.txt
eea.volto.policy.egg-info/top_level.txt
eea/volto/__init__.py
eea/volto/policy/README.txt
eea/volto/policy/__init__.py
eea/volto/policy/configure.zcml
eea/volto/policy/indexers.py
eea/volto/policy/inherit.py
eea/volto/policy/interfaces.py
eea/volto/policy/overrides.zcml
eea/volto/policy/permissions.zcml
eea/volto/policy/profiles.zcml
eea/volto/policy/setuphandlers.py
eea/volto/policy/subscribers.py
eea/volto/policy/utils.py
eea/volto/policy/version.txt
eea/volto/policy/behaviors/__init__.py
eea/volto/policy/behaviors/configure.zcml
eea/volto/policy/behaviors/enhanced_navigation.py
eea/volto/policy/behaviors/sidenavigation.py
eea/volto/policy/browser/__init__.py
eea/volto/policy/browser/breadcrumbs.py
eea/volto/policy/browser/configure.zcml
eea/volto/policy/browser/controlpanel.py
eea/volto/policy/browser/image.py
eea/volto/policy/browser/teaser.py
eea/volto/policy/browser/update_internal_api_path.py
eea/volto/policy/contentrules/__init__.py
eea/volto/policy/contentrules/actions.py
eea/volto/policy/contentrules/configure.zcml
eea/volto/policy/image_scales/__init__.py
eea/volto/policy/image_scales/adapters.py
eea/volto/policy/image_scales/configure.zcml
eea/volto/policy/image_scales/indexer.py
eea/volto/policy/image_scales/interfaces.py
eea/volto/policy/locales/__init__.py
eea/volto/policy/locales/eea.pot
eea/volto/policy/locales/plone-manual.pot
eea/volto/policy/locales/update.sh
eea/volto/policy/locales/bg/LC_MESSAGES/eea.mo
eea/volto/policy/locales/bg/LC_MESSAGES/eea.po
eea/volto/policy/locales/bg/LC_MESSAGES/plone.mo
eea/volto/policy/locales/bg/LC_MESSAGES/plone.po
eea/volto/policy/locales/cs/LC_MESSAGES/eea.mo
eea/volto/policy/locales/cs/LC_MESSAGES/eea.po
eea/volto/policy/locales/cs/LC_MESSAGES/plone.mo
eea/volto/policy/locales/cs/LC_MESSAGES/plone.po
eea/volto/policy/locales/da/LC_MESSAGES/eea.mo
eea/volto/policy/locales/da/LC_MESSAGES/eea.po
